<annotation>
	<folder>JPEGImages</folder>
	<filename>299.jpg</filename>
	<path>E:\VOC2007\JPEGImages\299.jpg</path>
	<source>
		<database>Unknown</database>
	</source>
	<size>
		<width>524</width>
		<height>128</height>
		<depth>1</depth>
	</size>
	<segmented>0</segmented>
	<object>
		<name>positive</name>
		<pose>Unspecified</pose>
		<truncated>0</truncated>
		<difficult>0</difficult>
		<bndbox>
			<xmin>310</xmin>
			<ymin>33</ymin>
			<xmax>336</xmax>
			<ymax>50</ymax>
		</bndbox>
	</object>
</annotation>
